README.rst
setup.cfg
setup.py
neuronjs/__init__.py
neuronjs/main.py
neuronjs/module.py
neuronjs/tools.py
neuronjs/walker.py
neuronjs.egg-info/PKG-INFO
neuronjs.egg-info/SOURCES.txt
neuronjs.egg-info/dependency_links.txt
neuronjs.egg-info/top_level.txt