Metadata-Version: 1.1
Name: neuronjs
Version: 2.1.0
Summary: The python middleware for neuron.js
Home-page: https://github.com/kaelzhang/python-neuronjs
Author: Kael Zhang
Author-email: i@kael.me
License: MIT
Keywords: neuron.js middleware javascript loader facade
Platform: UNKNOWN
Classifier: Programming Language :: Python
Classifier: Programming Language :: Python :: 2.6
Classifier: Programming Language :: Python :: 2.7
Classifier: Programming Language :: Python :: Implementation :: PyPy
Classifier: Topic :: Utilities
Classifier: License :: OSI Approved :: MIT License
